LICENSE
MANIFEST.in
README.rst
setup.py
django_sentry.egg-info/PKG-INFO
django_sentry.egg-info/SOURCES.txt
django_sentry.egg-info/dependency_links.txt
django_sentry.egg-info/entry_points.txt
django_sentry.egg-info/not-zip-safe
django_sentry.egg-info/requires.txt
django_sentry.egg-info/top_level.txt
sentry/__init__.py
sentry/filters.py
sentry/models.py
sentry/search_indexes.py
sentry/signals.py
sentry/wsgi.py
sentry/client/__init__.py
sentry/client/async.py
sentry/client/base.py
sentry/client/handlers.py
sentry/client/middleware.py
sentry/client/models.py
sentry/client/celery/__init__.py
sentry/client/celery/client.py
sentry/client/celery/conf.py
sentry/client/celery/models.py
sentry/client/celery/tasks.py
sentry/client/log/__init__.py
sentry/conf/__init__.py
sentry/conf/defaults.py
sentry/conf/server.py
sentry/conf/settings.py
sentry/migrations/0001_initial.py
sentry/migrations/0002_auto__del_field_groupedmessage_url__chg_field_groupedmessage_view__chg.py
sentry/migrations/0003_auto__add_field_message_group__del_field_groupedmessage_server_name.py
sentry/migrations/0004_auto__add_filtervalue__add_unique_filtervalue_key_value.py
sentry/migrations/0005_auto.py
sentry/migrations/0006_auto.py
sentry/migrations/0007_auto__add_field_message_site.py
sentry/migrations/0008_auto__chg_field_message_view__add_field_groupedmessage_data__chg_field.py
sentry/migrations/0009_auto__add_field_message_message_id.py
sentry/migrations/0010_auto__add_messageindex__add_unique_messageindex_column_value_object_id.py
sentry/migrations/0011_auto__add_field_groupedmessage_score.py
sentry/migrations/0012_auto.py
sentry/migrations/0013_auto__add_messagecountbyminute__add_unique_messagecountbyminute_group_.py
sentry/migrations/0014_auto.py
sentry/migrations/__init__.py
sentry/plugins/__init__.py
sentry/plugins/sentry_redmine/__init__.py
sentry/plugins/sentry_redmine/conf.py
sentry/plugins/sentry_redmine/models.py
sentry/plugins/sentry_redmine/migrations/0001_initial.py
sentry/plugins/sentry_redmine/migrations/__init__.py
sentry/plugins/sentry_redmine/templates/sentry/plugins/redmine/create_issue.html
sentry/plugins/sentry_redmine/tests/__init__.py
sentry/plugins/sentry_servers/__init__.py
sentry/plugins/sentry_servers/models.py
